leaderbot/__init__.py
leaderbot/__version__.py
leaderbot/_visualization/__init__.py
leaderbot/_visualization/_plot_cluster.py
leaderbot/_visualization/_plot_map_distance.py
leaderbot/_visualization/_plot_marginal_outcomes.py
leaderbot/_visualization/_plot_match_matrix.py
leaderbot/_visualization/_plot_scores.py
leaderbot/_visualization/_plot_util.py
leaderbot/data/__init__.py
leaderbot/data/_util.py
leaderbot/data/chatbotarena_20240814.json
leaderbot/data/convert.py
leaderbot/data/load.py
leaderbot/data/sample_whitelist.py
leaderbot/data/split.py
leaderbot/evaluate/__init__.py
leaderbot/evaluate/_util.py
leaderbot/evaluate/compare_ranks.py
leaderbot/evaluate/generalization.py
leaderbot/evaluate/goodness_of_fit.py
leaderbot/evaluate/model_selection.py
leaderbot/models/__init__.py
leaderbot/models/_base_interface.py
leaderbot/models/_base_model.py
leaderbot/models/_bradleyterry_factor_cov.py
leaderbot/models/_bradleyterry_no_cov.py
leaderbot/models/_bradleyterry_scaled.py
leaderbot/models/_bradleyterry_scaled_r.py
leaderbot/models/_bradleyterry_scaled_rij.py
leaderbot/models/_davidson_factor_cov.py
leaderbot/models/_davidson_no_cov.py
leaderbot/models/_davidson_scaled.py
leaderbot/models/_davidson_scaled_r.py
leaderbot/models/_davidson_scaled_rij.py
leaderbot/models/_factor_model.py
leaderbot/models/_math_util.py
leaderbot/models/_raokupper_factor_cov.py
leaderbot/models/_raokupper_no_cov.py
leaderbot/models/_raokupper_scaled.py
leaderbot/models/_raokupper_scaled_r.py
leaderbot/models/_raokupper_scaled_rij.py
leaderbot/models/bradleyterry.py
leaderbot/models/davidson.py
leaderbot/models/raokupper.py
leaderbot-0.4.3.dist-info/licenses/LICENSE.txt
leaderbot-0.4.3.dist-info/METADATA
leaderbot-0.4.3.dist-info/WHEEL
leaderbot-0.4.3.dist-info/top_level.txt
leaderbot-0.4.3.dist-info/RECORD
